{
    "@class": "com.kony.gen.viz.model.component.KVizTextBox2",
    "DNDConfig": null,
    "__parentReadjusting__": false,
    "_bottom_": {
        "type": "string",
        "value": "5dp"
    },
    "_left_": {
        "type": "string",
        "value": "10dp"
    },
    "_margin_": [
        0,
        0,
        0,
        0
    ],
    "_padding_": [
        3,
        0,
        0,
        0
    ],
    "_placeholder_": "Phone Number",
    "_right_": {
        "type": "string",
        "value": "10dp"
    },
    "_skin_": "s90ffecaa05a4f3da3a57f18674e005f",
    "_text_": "",
    "_top_": {
        "type": "string",
        "value": "5dp"
    },
    "android": {},
    "autocapitalize": "none",
    "autocomplete": false,
    "autocorrect": false,
    "autofilter": false,
    "canUpdateUI": true,
    "containerheight": "",
    "containerheightmode": 1,
    "containerweight": 100,
    "contentalignment": 4,
    "disabledSkins": {},
    "focusskin": "s34352f0e1c04377a7404ccd4a6fbdda",
    "id": "txtPhone",
    "info": null,
    "iphone": {
        "psp": {
            "showClearButton": false
        }
    },
    "isvisible": true,
    "keyboardstyle": "A",
    "keyboardtype": "A",
    "kuid": "a19a2b20bd3e471fa8f31cc9bc3c183c",
    "masterType": 1,
    "mode": "N",
    "name": "kony.ui.TextBox2",
    "paddinginpixel": false,
    "parent": "FlxContainerPhone",
    "pf": "LogupPage",
    "placeholderskin": "se3ee2dec87041e4b2deaecf880b7e3d",
    "securetextentry": false,
    "showclearbutton": false,
    "textinputmode": "N",
    "tooltip": "",
    "viewtype": "default",
    "wType": "TextField",
    "zindex": 1
}